SC16IS750/SC16IS750.py
SC16IS750/__init__.py
SC16IS750-0.1.8.dist-info/METADATA
SC16IS750-0.1.8.dist-info/WHEEL
SC16IS750-0.1.8.dist-info/top_level.txt
SC16IS750-0.1.8.dist-info/RECORD
