Metadata-Version: 2.1
Name: SC16IS750
Version: 0.1.8
Summary: Python driver for interfacing with the SC16IS750
Home-page: https://github.com/Harri-Renney/SC16IS750
Author: harri.renney.blino
Author-email: harri.renney@blino.co.uk
License: TODO
Platform: UNKNOWN
Classifier: Programming Language :: Python :: 3
Classifier: License :: OSI Approved :: MIT License
Classifier: Operating System :: OS Independent
